Metadata-Version: 2.4
Name: netbox-device-support-plugin
Version: 1.0.22
Summary: Cisco device support, device type support, and software release information with the Cisco support APIs
Author: Willi Kubny
Author-email: willi.kubny@gmail.com
License: MIT
Classifier: Programming Language :: Python :: 3
Classifier: Framework :: Django
Classifier: Intended Audience :: Information Technology
Classifier: License :: OSI Approved :: MIT License
Classifier: Operating System :: OS Independent
Classifier: Topic :: System :: Networking
Classifier: Topic :: System :: Systems Administration
License-File: LICENSE
Dynamic: author
Dynamic: author-email
Dynamic: classifier
Dynamic: description
Dynamic: description-content-type
Dynamic: license
Dynamic: license-file
Dynamic: summary
